simple_googletrans/__init__.py
simple_googletrans/version.json
simple_googletrans-1.0.2.dist-info/METADATA
simple_googletrans-1.0.2.dist-info/WHEEL
simple_googletrans-1.0.2.dist-info/entry_points.txt
simple_googletrans-1.0.2.dist-info/top_level.txt
simple_googletrans-1.0.2.dist-info/RECORD
