Metadata-Version: 2.1
Name: simple-googletrans
Version: 1.0.2
Summary: A simple wrapper of googletrans
Home-page: https://github.com/suqingdong/simple-googletrans
Author: suqingdong
Author-email: 1078595229@qq.com
License: BSD License
Project-URL: Tracker, https://github.com/suqingdong/simple-googletrans/issues
Platform: UNKNOWN
Classifier: Development Status :: 5 - Production/Stable
Classifier: Operating System :: OS Independent
Classifier: Intended Audience :: Developers
Classifier: License :: OSI Approved :: BSD License
Classifier: Programming Language :: Python
Classifier: Programming Language :: Python :: 2
Classifier: Programming Language :: Python :: 2.7
Classifier: Programming Language :: Python :: 3
Classifier: Programming Language :: Python :: 3.6
Classifier: Topic :: Software Development :: Libraries
Requires-Dist: click
Requires-Dist: googletrans (>=4.0.0-rc1)
Requires-Dist: prettytable
Requires-Dist: simple-loggers
